{"ย้าย": [{"text": ["รถ-NOUN", "รถ-NOUN", "รถ-NOUN", "ไม่ย้าย-NOUN", "การ-NOUN", "ภัย-NOUN", "นวด-NOUN"]}, {"wordNoun": ["รถ-NOUN", "รถ-NOUN", "รถ-NOUN", "ไม่ย้าย-NOUN", "การ-NOUN", "ภัย-NOUN", "นวด-NOUN"]}, {"count": ["รถ-NOUN", "รถ-NOUN", "รถ-NOUN", "ไม่ย้าย-NOUN", "การ-NOUN", "ภัย-NOUN", "นวด-NOUN"]}], "รถ": [{"text": ["รถ-NOUN", "รถ-NOUN", "รถ-NOUN", "ไม่ย้าย-NOUN", "การ-NOUN", "ภัย-NOUN", "นวด-NOUN"]}, {"wordNoun": ["รถ-NOUN", "รถ-NOUN", "รถ-NOUN", "ไม่ย้าย-NOUN", "การ-NOUN", "ภัย-NOUN", "นวด-NOUN"]}, {"count": ["รถ-NOUN", "รถ-NOUN", "รถ-NOUN", "ไม่ย้าย-NOUN", "การ-NOUN", "ภัย-NOUN", "นวด-NOUN"]}], "รบกวน": [{"text": ["รถ-NOUN", "รถ-NOUN", "รถ-NOUN", "ไม่ย้าย-NOUN", "การ-NOUN", "ภัย-NOUN", "นวด-NOUN"]}, {"wordNoun": ["รถ-NOUN", "รถ-NOUN", "รถ-NOUN", "ไม่ย้าย-NOUN", "การ-NOUN", "ภัย-NOUN", "นวด-NOUN"]}, {"count": ["รถ-NOUN", "รถ-NOUN", "รถ-NOUN", "ไม่ย้าย-NOUN", "การ-NOUN", "ภัย-NOUN", "นวด-NOUN"]}], "รวดเร็ว": [{"text": ["รถ-NOUN", "รถ-NOUN", "รถ-NOUN", "ไม่ย้าย-NOUN", "การ-NOUN", "ภัย-NOUN", "นวด-NOUN"]}, {"wordNoun": ["รถ-NOUN", "รถ-NOUN", "รถ-NOUN", "ไม่ย้าย-NOUN", "การ-NOUN", "ภัย-NOUN", "นวด-NOUN"]}, {"count": ["รถ-NOUN", "รถ-NOUN", "รถ-NOUN", "ไม่ย้าย-NOUN", "การ-NOUN", "ภัย-NOUN", "นวด-NOUN"]}], "รวบรวม": [{"text": ["รถ-NOUN", "รถ-NOUN", "รถ-NOUN", "ไม่ย้าย-NOUN", "การ-NOUN", "ภัย-NOUN", "นวด-NOUN"]}, {"wordNoun": ["รถ-NOUN", "รถ-NOUN", "รถ-NOUN", "ไม่ย้าย-NOUN", "การ-NOUN", "ภัย-NOUN", "นวด-NOUN"]}, {"count": ["รถ-NOUN", "รถ-NOUN", "รถ-NOUN", "ไม่ย้าย-NOUN", "การ-NOUN", "ภัย-NOUN", "นวด-NOUN"]}], "รวม": [{"text": ["รถ-NOUN", "รถ-NOUN", "รถ-NOUN", "ไม่ย้าย-NOUN", "การ-NOUN", "ภัย-NOUN", "นวด-NOUN"]}, {"wordNoun": ["รถ-NOUN", "รถ-NOUN", "รถ-NOUN", "ไม่ย้าย-NOUN", "การ-NOUN", "ภัย-NOUN", "นวด-NOUN"]}, {"count": ["รถ-NOUN", "รถ-NOUN", "รถ-NOUN", "ไม่ย้าย-NOUN", "การ-NOUN", "ภัย-NOUN", "นวด-NOUN"]}], "รส": [{"text": ["รถ-NOUN", "รถ-NOUN", "รถ-NOUN", "ไม่ย้าย-NOUN", "การ-NOUN", "ภัย-NOUN", "นวด-NOUN"]}, {"wordNoun": ["รถ-NOUN", "รถ-NOUN", "รถ-NOUN", "ไม่ย้าย-NOUN", "การ-NOUN", "ภัย-NOUN", "นวด-NOUN"]}, {"count": ["รถ-NOUN", "รถ-NOUN", "รถ-NOUN", "ไม่ย้าย-NOUN", "การ-NOUN", "ภัย-NOUN", "นวด-NOUN"]}]}